swarmauri_keyprovider_hierarchical/HierarchicalKeyProvider.py
swarmauri_keyprovider_hierarchical/__init__.py
swarmauri_keyprovider_hierarchical-0.3.0.dev4.dist-info/LICENSE
swarmauri_keyprovider_hierarchical-0.3.0.dev4.dist-info/METADATA
swarmauri_keyprovider_hierarchical-0.3.0.dev4.dist-info/WHEEL
swarmauri_keyprovider_hierarchical-0.3.0.dev4.dist-info/entry_points.txt
swarmauri_keyprovider_hierarchical-0.3.0.dev4.dist-info/RECORD
